cardinity/__init__.py
cardinity/auth.py
cardinity/client.py
cardinity/exceptions.py
cardinity/sdk.py
cardinity/models/__init__.py
cardinity/models/base.py
cardinity/models/chargeback.py
cardinity/models/finalize_payment.py
cardinity/models/get_payment.py
cardinity/models/payment.py
cardinity/models/payment_link.py
cardinity/models/recurring_payment.py
cardinity/models/refund.py
cardinity/models/settlement.py
cardinity/models/void.py
cardinity/utils/__init__.py
cardinity/validation/__init__.py
cardinity/validation/constraints.py
cardinity/validation/validators.py
cardinity_python-1.0.4.dist-info/METADATA
cardinity_python-1.0.4.dist-info/WHEEL
cardinity_python-1.0.4.dist-info/licenses/LICENSE
cardinity_python-1.0.4.dist-info/RECORD
