Metadata-Version: 2.4
Name: cardinity-python
Version: 1.0.4
Summary: Python SDK for Cardinity Payment Gateway API
Project-URL: Homepage, https://github.com/trendpro/cardinity-python
Project-URL: Documentation, https://cardinity-python.readthedocs.io/
Project-URL: Repository, https://github.com/trendpro/cardinity-python
Project-URL: Bug Tracker, https://github.com/trendpro/cardinity-python/issues
Project-URL: Changelog, https://github.com/trendpro/cardinity-python/blob/main/CHANGELOG.md
Author-email: Kyalo Kitili <kyalo@trendpro.co.ke>
Maintainer-email: Kyalo Kitili <kyalo@trendpro.co.ke>
License: MIT
License-File: LICENSE
Keywords: api,cardinity,gateway,payment,sdk
Classifier: Development Status :: 5 - Production/Stable
Classifier: Intended Audience :: Developers
Classifier: License :: OSI Approved :: MIT License
Classifier: Operating System :: OS Independent
Classifier: Programming Language :: Python :: 3
Classifier: Programming Language :: Python :: 3.8
Classifier: Programming Language :: Python :: 3.9
Classifier: Programming Language :: Python :: 3.10
Classifier: Programming Language :: Python :: 3.11
Classifier: Programming Language :: Python :: 3.12
Classifier: Topic :: Office/Business :: Financial
Classifier: Topic :: Software Development :: Libraries :: Python Modules
Requires-Python: >=3.8
Requires-Dist: cerberus>=1.3.0
Requires-Dist: python-dateutil>=2.8.0
Requires-Dist: requests-oauthlib>=1.3.0
Requires-Dist: requests>=2.25.0
Provides-Extra: dev
Requires-Dist: mypy>=0.800; extra == 'dev'
Requires-Dist: pytest-cov>=2.0; extra == 'dev'
Requires-Dist: pytest>=6.0; extra == 'dev'
Requires-Dist: ruff>=0.1.0; extra == 'dev'
Requires-Dist: sphinx-rtd-theme>=0.5; extra == 'dev'
Requires-Dist: sphinx>=4.0; extra == 'dev'
